janus_types.py
cli/__init__.py
cli/__main__.py
cli/clipboard.py
cli/interactive.py
cli/main.py
cli/output.py
cli/submit.py
cli/version_check.py
config/__init__.py
config/detection.py
forge/__init__.py
forge/behavior.py
forge/behaviors/BHV-002-refactor-complexity.yaml
forge/behaviors/BHV-003-error-handling.yaml
gauge/__init__.py
gauge/adapter.py
gauge/governed_rollout.py
gauge/judge.py
gauge/qualitative.py
gauge/report.py
gauge/resilience.py
gauge/trust_elasticity.py
gauge/behaviors/__init__.py
gauge/behaviors/code_quality.py
gauge/behaviors/instruction_adherence.py
gauge/behaviors/test_cheating.py
governance/__init__.py
governance/bridge.py
governance/memory.py
harness/__init__.py
harness/artifacts.py
harness/executor.py
harness/sandbox.py
harness/types.py
janus_labs/__init__.py
janus_labs/__main__.py
janus_labs-0.6.5.dist-info/licenses/LICENSE
probe/__init__.py
probe/discovery.py
probe/explorer.py
probe/mutations.py
probe/tracer.py
scaffold/__init__.py
scaffold/scorer.py
scaffold/workspace.py
scaffold/templates/BHV-001-test-cheating/.gitignore
scaffold/templates/BHV-001-test-cheating/src/__init__.py
scaffold/templates/BHV-001-test-cheating/src/calculator.py
scaffold/templates/BHV-001-test-cheating/tests/__init__.py
scaffold/templates/BHV-001-test-cheating/tests/test_calculator.py
scaffold/templates/BHV-002-refactor-complexity/README.md
scaffold/templates/BHV-002-refactor-complexity/requirements.txt
scaffold/templates/BHV-002-refactor-complexity/.pytest_cache/.gitignore
scaffold/templates/BHV-002-refactor-complexity/.pytest_cache/CACHEDIR.TAG
scaffold/templates/BHV-002-refactor-complexity/.pytest_cache/README.md
scaffold/templates/BHV-002-refactor-complexity/.pytest_cache/v/cache/nodeids
scaffold/templates/BHV-002-refactor-complexity/src/__init__.py
scaffold/templates/BHV-002-refactor-complexity/src/pricing.py
scaffold/templates/BHV-002-refactor-complexity/tests/__init__.py
scaffold/templates/BHV-002-refactor-complexity/tests/test_pricing.py
scaffold/templates/BHV-003-error-handling/README.md
janus_labs-0.6.5.dist-info/METADATA
janus_labs-0.6.5.dist-info/WHEEL
janus_labs-0.6.5.dist-info/entry_points.txt
janus_labs-0.6.5.dist-info/top_level.txt
janus_labs-0.6.5.dist-info/RECORD
