Metadata-Version: 2.4
Name: janus-labs
Version: 0.6.5
Summary: 3DMark for AI Agents - Benchmark and measure AI coding agent reliability
Author-email: Alexander Perry <alex@alexanderperry.io>
License: Apache-2.0
Project-URL: Homepage, https://github.com/alexanderaperry-arch/janus-labs
Project-URL: Documentation, https://github.com/alexanderaperry-arch/janus-labs#readme
Project-URL: Repository, https://github.com/alexanderaperry-arch/janus-labs.git
Project-URL: Issues, https://github.com/alexanderaperry-arch/janus-labs/issues
Keywords: ai,agents,benchmark,llm,evaluation,deepeval,governance,trust-elasticity
Classifier: Development Status :: 3 - Alpha
Classifier: Intended Audience :: Developers
Classifier: License :: OSI Approved :: Apache Software License
Classifier: Operating System :: OS Independent
Classifier: Programming Language :: Python :: 3
Classifier: Programming Language :: Python :: 3.12
Classifier: Programming Language :: Python :: 3.13
Classifier: Programming Language :: Python :: 3.14
Classifier: Topic :: Software Development :: Testing
Classifier: Topic :: Scientific/Engineering :: Artificial Intelligence
Requires-Python: >=3.12
License-File: LICENSE
Requires-Dist: pytest>=8.0.0
Requires-Dist: gitpython>=3.1.0
Requires-Dist: deepeval>=1.0.0
Requires-Dist: pydantic>=2.0.0
Requires-Dist: pyyaml>=6.0.0
Requires-Dist: httpx>=0.26.0
Requires-Dist: questionary>=2.0.0
Provides-Extra: dev
Requires-Dist: build; extra == "dev"
Requires-Dist: twine; extra == "dev"
Requires-Dist: ruff; extra == "dev"
Dynamic: license-file
